sym/sdk/__init__.py
sym/sdk/annotations/__init__.py
sym/sdk/annotations/_handlers.py
sym/sdk/errors.py
sym/sdk/event.py
sym/sdk/exceptions/__init__.py
sym/sdk/exceptions/access_strategy.py
sym/sdk/exceptions/aptible.py
sym/sdk/exceptions/aws.py
sym/sdk/exceptions/boundary.py
sym/sdk/exceptions/github.py
sym/sdk/exceptions/google.py
sym/sdk/exceptions/http.py
sym/sdk/exceptions/identity.py
sym/sdk/exceptions/jira.py
sym/sdk/exceptions/knowbe4.py
sym/sdk/exceptions/okta.py
sym/sdk/exceptions/onelogin.py
sym/sdk/exceptions/pagerduty.py
sym/sdk/exceptions/sdk.py
sym/sdk/exceptions/slack.py
sym/sdk/exceptions/sym_exception.py
sym/sdk/exceptions/sym_integration.py
sym/sdk/field_option.py
sym/sdk/flow.py
sym/sdk/forms.py
sym/sdk/integrations/__init__.py
sym/sdk/integrations/aws_iam.py
sym/sdk/integrations/aws_lambda.py
sym/sdk/integrations/aws_sso.py
sym/sdk/integrations/boundary.py
sym/sdk/integrations/github.py
sym/sdk/integrations/google.py
sym/sdk/integrations/jira.py
sym/sdk/integrations/knowbe4.py
sym/sdk/integrations/okta.py
sym/sdk/integrations/onelogin.py
sym/sdk/integrations/pagerduty.py
sym/sdk/integrations/slack.py
sym/sdk/integrations/store.py
sym/sdk/integrations/sym.py
sym/sdk/models.py
sym/sdk/notifications.py
sym/sdk/request_destination.py
sym/sdk/request_permission.py
sym/sdk/resource.py
sym/sdk/secret.py
sym/sdk/strategies/__init__.py
sym/sdk/strategies/access_strategy.py
sym/sdk/strategies/integration.py
sym/sdk/strategy.py
sym/sdk/target.py
sym/sdk/templates/__init__.py
sym/sdk/templates/approval.py
sym/sdk/templates/step.py
sym/sdk/templates/template.py
sym/sdk/tests/__init__.py
sym/sdk/tests/annotations/__init__.py
sym/sdk/tests/annotations/test_reducer.py
sym/sdk/tests/integrations/__init__.py
sym/sdk/tests/integrations/test_pagerduty_interface.py
sym/sdk/tests/static/__init__.py
sym/sdk/tests/static/approvers_test_code.py
sym/sdk/tests/test_flow.py
sym/sdk/tests/test_forms.py
sym/sdk/tests/test_notifications.py
sym_sdk-0.61.0.dist-info/WHEEL
sym_sdk-0.61.0.dist-info/METADATA
sym_sdk-0.61.0.dist-info/LICENSE
sym_sdk-0.61.0.dist-info/RECORD
