Metadata-Version: 2.1
Name: sym-sdk
Version: 0.61.0
Summary: Sym's Python SDK
Home-page: https://sdk.docs.symops.com/
License: Proprietary
Author: Sym Engineering
Author-email: pypi@symops.io
Requires-Python: >=3.8.6,<4.0.0
Classifier: License :: Other/Proprietary License
Classifier: Operating System :: OS Independent
Classifier: Programming Language :: Python :: 3
Classifier: Programming Language :: Python :: 3.9
Classifier: Programming Language :: Python :: 3.10
Classifier: Programming Language :: Python :: 3.11
Classifier: Programming Language :: Python :: 3
Requires-Dist: pydantic (>=1.7.3,<2.0.0)
Project-URL: Repository, https://github.com/symopsio/sym-sdk
